d3fdgraph/__init__.py
d3fdgraph/d3fdgraph.html
d3fdgraph/d3fdgraph.js
d3fdgraph/d3fdgraph.py
d3fdgraph-0.34.dist-info/METADATA
d3fdgraph-0.34.dist-info/WHEEL
d3fdgraph-0.34.dist-info/top_level.txt
d3fdgraph-0.34.dist-info/RECORD
