Metadata-Version: 2.1
Name: d3fdgraph
Version: 0.34
Summary: Interactive force-directed graph in a jupyter notebook.
Home-page: https://github.com/intuitivetextmining/d3fdgraph
Author: Intuitive Text Mining
Author-email: intuitivetextmining@gmail.com
License: GPLv2
Platform: UNKNOWN
Requires-Dist: IPython
Requires-Dist: networkx
